hydra/__init__.py
hydra/compose.py
hydra/errors.py
hydra/initialize.py
hydra/main.py
hydra/py.typed
hydra/types.py
hydra/utils.py
hydra/version.py
hydra/_internal/__init__.py
hydra/_internal/callbacks.py
hydra/_internal/config_loader_impl.py
hydra/_internal/config_repository.py
hydra/_internal/config_search_path_impl.py
hydra/_internal/defaults_list.py
hydra/_internal/deprecation_warning.py
hydra/_internal/hydra.py
hydra/_internal/sources_registry.py
hydra/_internal/utils.py
hydra/_internal/core_plugins/__init__.py
hydra/_internal/core_plugins/bash_completion.py
hydra/_internal/core_plugins/basic_launcher.py
hydra/_internal/core_plugins/basic_sweeper.py
hydra/_internal/core_plugins/file_config_source.py
hydra/_internal/core_plugins/fish_completion.py
hydra/_internal/core_plugins/importlib_resources_config_source.py
hydra/_internal/core_plugins/structured_config_source.py
hydra/_internal/core_plugins/zsh_completion.py
hydra/_internal/grammar/__init__.py
hydra/_internal/grammar/functions.py
hydra/_internal/grammar/grammar_functions.py
hydra/_internal/grammar/utils.py
hydra/_internal/instantiate/__init__.py
hydra/_internal/instantiate/_instantiate2.py
hydra/conf/__init__.py
hydra/conf/hydra/env/default.yaml
hydra/conf/hydra/help/default.yaml
hydra/conf/hydra/hydra_help/default.yaml
hydra/conf/hydra/hydra_logging/default.yaml
hydra/conf/hydra/hydra_logging/disabled.yaml
hydra/conf/hydra/hydra_logging/hydra_debug.yaml
hydra/conf/hydra/hydra_logging/none.yaml
hydra/conf/hydra/job_logging/default.yaml
hydra/conf/hydra/job_logging/disabled.yaml
hydra/conf/hydra/job_logging/none.yaml
hydra/conf/hydra/job_logging/stdout.yaml
hydra/conf/hydra/output/default.yaml
hydra/core/__init__.py
hydra/core/config_loader.py
hydra/core/config_search_path.py
hydra/core/config_store.py
hydra/core/default_element.py
hydra/core/global_hydra.py
hydra/core/hydra_config.py
hydra/core/object_type.py
hydra/core/plugins.py
hydra/core/singleton.py
hydra/core/utils.py
ms_hydra_core_fork-1.6.0.dev1.dist-info/licenses/LICENSE
ms_hydra_core_fork-1.6.0.dev1.dist-info/METADATA
ms_hydra_core_fork-1.6.0.dev1.dist-info/WHEEL
ms_hydra_core_fork-1.6.0.dev1.dist-info/entry_points.txt
ms_hydra_core_fork-1.6.0.dev1.dist-info/top_level.txt
ms_hydra_core_fork-1.6.0.dev1.dist-info/RECORD
