Metadata-Version: 2.4
Name: ms-hydra-core-fork
Version: 1.6.0.dev1
Summary: A framework for elegantly configuring complex applications
Home-page: https://github.com/facebookresearch/hydra
Author: Omry Yadan
Author-email: omry@fb.com
License: MIT
Keywords: command-line configuration yaml tab-completion
Classifier: License :: OSI Approved :: MIT License
Classifier: Development Status :: 4 - Beta
Classifier: Programming Language :: Python :: 3.8
Classifier: Programming Language :: Python :: 3.9
Classifier: Programming Language :: Python :: 3.10
Classifier: Programming Language :: Python :: 3.11
Classifier: Operating System :: POSIX :: Linux
Classifier: Operating System :: MacOS
Classifier: Operating System :: Microsoft :: Windows
License-File: LICENSE
Requires-Dist: ms-omegaconf-fork
Requires-Dist: importlib-resources; python_version < "3.9"
Requires-Dist: packaging
Dynamic: author
Dynamic: author-email
Dynamic: classifier
Dynamic: description
Dynamic: description-content-type
Dynamic: home-page
Dynamic: keywords
Dynamic: license
Dynamic: license-file
Dynamic: requires-dist
Dynamic: summary
